IDEAS.txt
LICENSE.txt
MANIFEST.in
README.txt
pavement.py
paver-minilib.zip
setup.py
metamake/__init__.py
metamake/_bootstrap.py
metamake/_dependencies.py
metamake/_flags.py
metamake/_path.py
metamake/_shell.py
metamake.egg-info/PKG-INFO
metamake.egg-info/SOURCES.txt
metamake.egg-info/dependency_links.txt
metamake.egg-info/entry_points.txt
metamake.egg-info/not-zip-safe
metamake.egg-info/top_level.txt
tests/Makefile.py
tests/Makefile.pyc
tests/__init__.py
tests/__init__.pyc
tests/main.py
tests/test_bootstrap.py
tests/test_bootstrap.pyc
tests/test_flags.py
tests/test_flags.pyc
tests/test_shell.py
tests/test_shell.pyc