Metadata-Version: 1.0
Name: metamake
Version: 1.0.9
Summary: Metamake is a dead-simple task-based automation tool written in Python.
Home-page: http://pypi.python.org/pypi/metamake/
Author: Matt Pizzimenti
Author-email: mjpizz+metamake@gmail.com
License: BSD
Platform: UNKNOWN
